causalimpact/__init__.py
causalimpact/__version__.py
causalimpact/data.py
causalimpact/inferences.py
causalimpact/main.py
causalimpact/misc.py
causalimpact/model.py
causalimpact/plot.py
causalimpact/summary.py
causalimpact/summary/templates/report
causalimpact/summary/templates/summary
tfcausalimpact-0.0.18.dist-info/LICENSE
tfcausalimpact-0.0.18.dist-info/METADATA
tfcausalimpact-0.0.18.dist-info/WHEEL
tfcausalimpact-0.0.18.dist-info/top_level.txt
tfcausalimpact-0.0.18.dist-info/RECORD
