Metadata-Version: 2.2
Name: tfcausalimpact
Version: 0.0.18
Summary: Python version of Google's Causal Impact model on top of Tensorflow Probability.
Home-page: https://github.com/WillianFuks/tfcausalimpact
Author: Willian Fuks
Author-email: willian.fuks@gmail.com
License: Apache License 2.0
Project-URL: Source, https://github.com/WillianFuks/tfcausalimpact
Keywords: causal impact
Classifier: Development Status :: 3 - Alpha
Classifier: Environment :: Console
Classifier: Intended Audience :: Developers
Classifier: Intended Audience :: Education
Classifier: Intended Audience :: Science/Research
Classifier: License :: OSI Approved :: Apache Software License
Classifier: Natural Language :: English
Classifier: Operating System :: POSIX :: Linux
Classifier: Operating System :: MacOS
Classifier: Operating System :: Microsoft :: Windows
Classifier: Programming Language :: Python :: 3.8
Classifier: Programming Language :: Python :: 3.9
Classifier: Programming Language :: Python :: 3.10
Classifier: Programming Language :: Python :: 3.11
Classifier: Programming Language :: Python :: 3.12
Classifier: Programming Language :: Python :: Implementation :: CPython
Classifier: Topic :: Scientific/Engineering
Requires-Python: >=3, <3.13
License-File: LICENSE
Requires-Dist: jinja2
Requires-Dist: pandas<=2.2,>=1.3.5
Requires-Dist: tensorflow>=2.10
Requires-Dist: tensorflow-probability[tf]<=0.25,>=0.18
Requires-Dist: matplotlib
Provides-Extra: docs
Requires-Dist: ipython; extra == "docs"
Requires-Dist: jupyter; extra == "docs"
Dynamic: author
Dynamic: author-email
Dynamic: classifier
Dynamic: description
Dynamic: description-content-type
Dynamic: home-page
Dynamic: keywords
Dynamic: license
Dynamic: project-url
Dynamic: provides-extra
Dynamic: requires-dist
Dynamic: requires-python
Dynamic: summary
